spectr/__init__.py
spectr/__main__.py
spectr/app.py
spectr/app.tcss
spectr/config.py
spectr/confirmation_modal.py
spectr/confirmation_modal.tcss
spectr/conflict_resolution_screen.tcss
spectr/copy_screen.py
spectr/copy_screen.tcss
spectr/downsample.py
spectr/file_preview.py
spectr/file_stats.py
spectr/file_table.py
spectr/main.py
spectr/query_screen.py
spectr/query_screen.tcss
spectr/types.py
spectr-0.4a1.dist-info/WHEEL
spectr-0.4a1.dist-info/entry_points.txt
spectr-0.4a1.dist-info/METADATA
spectr-0.4a1.dist-info/RECORD
