Metadata-Version: 2.3
Name: spectr
Version: 0.4a1
Summary: A TUI for browsing Analyzer4D data stream files
Author: Ossmos
Requires-Dist: numpy>=2.3.4
Requires-Dist: plotext>=5.3.2
Requires-Dist: pydantic>=2.12.4
Requires-Dist: pydantic-settings>=2.12.0
Requires-Dist: qass-tools-analyzer>=2.6
Requires-Dist: textual>=6.5.0
Requires-Dist: textual-plotext>=1.0.1
Requires-Dist: toml>=0.10.2
Requires-Dist: typer>=0.21.1
Requires-Python: >=3.11
Project-URL: Homepage, https://github.com/ossmos/spectr
